LICENSE
MANIFEST.in
README.rst
setup.py
Mopidy_Headless.egg-info/PKG-INFO
Mopidy_Headless.egg-info/SOURCES.txt
Mopidy_Headless.egg-info/dependency_links.txt
Mopidy_Headless.egg-info/entry_points.txt
Mopidy_Headless.egg-info/not-zip-safe
Mopidy_Headless.egg-info/requires.txt
Mopidy_Headless.egg-info/top_level.txt
mopidy_headless/__init__.py
mopidy_headless/decorator.py
mopidy_headless/ext.conf
mopidy_headless/frontend.py
mopidy_headless/input.py