Metadata-Version: 1.0
Name: Mopidy-Headless
Version: 0.2.0
Summary: Mopidy extension for controlling via input devices
Home-page: https://github.com/qurben/mopidy-headless
Author: Gerben Oolbekkink
Author-email: g.j.w.oolbekkink@gmail.com
License: Apache License, Version 2.0
Platform: UNKNOWN
